{
  "showSummaryCards": true,

  "sections": {
    "servizi": {
      "icon": "bi-grid-3x3-gap",
      "borderColor": "#3b7ddd",
      "summary": {
        "gradientFrom": "#3b7ddd",
        "gradientTo": "#2c5ea0",
        "textColor": "#ffffff"
      }
    },
    "adesioni": {
      "icon": "bi-display",
      "borderColor": "#1cbb8c",
      "summary": {
        "gradientFrom": "#1cbb8c",
        "gradientTo": "#158c69",
        "textColor": "#ffffff"
      }
    },
    "client": {
      "icon": "bi-person",
      "borderColor": "#6f42c1",
      "summary": {
        "gradientFrom": "#6f42c1",
        "gradientTo": "#553098",
        "textColor": "#ffffff"
      }
    },
    "comunicazioni": {
      "icon": "bi-chat-dots",
      "borderColor": "#fcb92c",
      "summary": {
        "gradientFrom": "#fcb92c",
        "gradientTo": "#e0a020",
        "textColor": "#212529"
      }
    },
    "utenti": {
      "icon": "bi-people",
      "borderColor": "#17a2b8",
      "summary": {
        "gradientFrom": "#17a2b8",
        "gradientTo": "#117a8b",
        "textColor": "#ffffff"
      }
    }
  }
}
